pinclr/__init__.py
codemaze-0.0.1.dist-info/METADATA
codemaze-0.0.1.dist-info/WHEEL
codemaze-0.0.1.dist-info/top_level.txt
codemaze-0.0.1.dist-info/RECORD
